odoo9_addon_partner_changeset-9.0.1.0.0-py2.7-nspkg.pth
odoo_addons/partner_changeset/__openerp__.py
odoo_addons/partner_changeset/__init__.py
odoo_addons/partner_changeset/README.rst
odoo_addons/partner_changeset/security/security.xml
odoo_addons/partner_changeset/security/ir.model.access.csv
odoo_addons/partner_changeset/models/res_partner.py
odoo_addons/partner_changeset/models/__init__.py
odoo_addons/partner_changeset/models/res_partner_changeset.py
odoo_addons/partner_changeset/models/changeset_field_rule.py
odoo_addons/partner_changeset/i18n/es.po
odoo_addons/partner_changeset/i18n/sl.po
odoo_addons/partner_changeset/i18n/partner_changeset.pot
odoo_addons/partner_changeset/i18n/fr.po
odoo_addons/partner_changeset/views/res_partner_views.xml
odoo_addons/partner_changeset/views/res_partner_changeset_views.xml
odoo_addons/partner_changeset/views/changeset_field_rule_views.xml
odoo_addons/partner_changeset/views/menu.xml
odoo_addons/partner_changeset/tests/test_changeset_field_type.py
odoo_addons/partner_changeset/tests/test_changeset_field_rule.py
odoo_addons/partner_changeset/tests/test_changeset_origin.py
odoo_addons/partner_changeset/tests/__init__.py
odoo_addons/partner_changeset/tests/common.py
odoo_addons/partner_changeset/tests/test_changeset_flow.py
odoo_addons/partner_changeset/demo/changeset_field_rule.xml
odoo_addons/partner_changeset/static/description/icon.png
odoo_addons/partner_changeset/static/src/img/changeset.png
odoo_addons/partner_changeset/static/src/img/rules.png
odoo9_addon_partner_changeset-9.0.1.0.0.dist-info/top_level.txt
odoo9_addon_partner_changeset-9.0.1.0.0.dist-info/WHEEL
odoo9_addon_partner_changeset-9.0.1.0.0.dist-info/RECORD
odoo9_addon_partner_changeset-9.0.1.0.0.dist-info/metadata.json
odoo9_addon_partner_changeset-9.0.1.0.0.dist-info/DESCRIPTION.rst
odoo9_addon_partner_changeset-9.0.1.0.0.dist-info/METADATA
odoo9_addon_partner_changeset-9.0.1.0.0.dist-info/namespace_packages.txt
